Workbook
Name order: 'Ecommerce_Raw_Data (2)'!$N$3
Name orders: 'Ecommerce_Raw_Data (2)'!$N$3

Sheet Ecommerce_Raw_Data (2)
A1: OrderID | B1: OrderDate | C1: Category | D1: Product | E1: State | F1: Quantity | G1: UnitPrice | H1: Discount% | I1: OrderStatus | J1: PaymentMode | K1: Channel | L1: OrderAmount | M1: month | N1: sales bucket
A2: OD20001 | B2: 45625 | C2: Home | D2: Wall Clock | E2: West Bengal | F2: 1 | G2: 718.62 | H2: 0 | I2: Delivered | J2: COD | K2: Website | L2: 718.62 | M2: =TEXT(B2,"mmm") -> Nov | N2: =IF(L2>20000,"high",IF(L2>10000,"medium","low")) -> low
A3: OD20002 | B3: 45322 | C3: Fashion | D3: T-Shirt | E3: West Bengal | F3: 5 | G3: 1121.85 | H3: 0.1 | I3: Pending | J3: Credit Card | K3: Website | L3: 5048.32 | M3: =TEXT(B3,"mmm") -> Jan | N3: =IF(L3>20000,"high",IF(L3>10000,"medium","low")) -> low | P3: discount change
A4: OD20003 | B4: 45506 | C4: Books | D4: Notebook | E4: Tamil Nadu | F4: 2 | G4: 4394.38 | H4: 0.1 | I4: Returned | J4: Debit Card | K4: Website | L4: 7909.88 | M4: =TEXT(B4,"mmm") -> Aug | N4: =IF(L4>20000,"high",IF(L4>10000,"medium","low")) -> low
A5: OD20004 | B5: 45608 | C5: Books | D5: Novel | E5: Delhi | F5: 2 | G5: 4046.85 | H5: 0.2 | I5: Delivered | J5: Credit Card | K5: Mobile App | L5: 6474.96 | M5: =TEXT(B5,"mmm") -> Nov | N5: =IF(L5>20000,"high",IF(L5>10000,"medium","low")) -> low | S5: 12344 | T5: text | U5: 234 | V5: =U5*1 -> 234
A6: OD20005 | B6: 45560 | C6: Electronics | D6: Phone Cover | E6: Tamil Nadu | F6: 4 | G6: 7019.83 | H6: 0.25 | I6: Delivered | J6: Debit Card | K6: Mobile App | L6: 21059.49 | M6: =TEXT(B6,"mmm") -> Sep | N6: =IF(L6>20000,"high",IF(L6>10000,"medium","low")) -> high | S6: 4562 | T6: no | U6: 321 | V6: =U6*1 -> 321
A7: OD20006 | B7: 45634 | C7: Beauty | D7: Hair Oil | E7: Delhi | F7: 1 | G7: 6151.88 | H7: 0.15 | I7: Delivered | J7: UPI | K7: Mobile App | L7: 5229.1 | M7: =TEXT(B7,"mmm") -> Dec | N7: =IF(L7>20000,"high",IF(L7>10000,"medium","low")) -> low | U7: 345 | V7: =U7*1 -> 345
A8: OD20007 | B8: 45651 | C8: Beauty | D8: Face Wash | E8: Delhi | F8: 3 | G8: 5229.96 | H8: 0.25 | I8: Delivered | J8: Debit Card | K8: Mobile App | L8: 11767.41 | M8: =TEXT(B8,"mmm") -> Dec | N8: =IF(L8>20000,"high",IF(L8>10000,"medium","low")) -> medium | U8: 2134 | V8: =U8*1 -> 2134
A9: OD20008 | B9: 45322 | C9: Books | D9: Novel | E9: Rajasthan | F9: 2 | G9: 6180.63 | H9: 0.05 | I9: Pending | J9: COD | K9: Mobile App | L9: 11743.2 | M9: =TEXT(B9,"mmm") -> Jan | N9: =IF(L9>20000,"high",IF(L9>10000,"medium","low")) -> medium | U9: 2 | V9: =U9*1 -> 2
A10: OD20009 | B10: 45512 | C10: Books | D10: Comic | E10: Karnataka | F10: 5 | G10: 2335.61 | H10: 0.2 | I10: Delivered | J10: Credit Card | K10: Mobile App | L10: 9342.44 | M10: =TEXT(B10,"mmm") -> Aug | N10: =IF(L10>20000,"high",IF(L10>10000,"medium","low")) -> low
A11: OD20010 | B11: 45593 | C11: Fashion | D11: T-Shirt | E11: Rajasthan | F11: 2 | G11: 2212.56 | H11: 0 | I11: Delivered | J11: Wallet | K11: Website | L11: 4425.12 | M11: =TEXT(B11,"mmm") -> Oct | N11: =IF(L11>20000,"high",IF(L11>10000,"medium","low")) -> low
A12: OD20011 | B12: 45495 | C12: Beauty | D12: Sunscreen | E12: West Bengal | F12: 4 | G12: 3243.84 | H12: 0.25 | I12: Pending | J12: UPI | K12: Mobile App | L12: 9731.52 | M12: =TEXT(B12,"mmm") -> Jul | N12: =IF(L12>20000,"high",IF(L12>10000,"medium","low")) -> low | U12: must multiply text no with 1
A13: OD20012 | B13: 45292 | C13: Books | D13: Novel | E13: Maharashtra | F13: 5 | G13: 1337.43 | H13: 0 | I13: Delivered | J13: Debit Card | K13: Mobile App | L13: 6687.15 | M13: =TEXT(B13,"mmm") -> Jan | N13: =IF(L13>20000,"high",IF(L13>10000,"medium","low")) -> low | U13: then drag theal ctrl +alt + v
A14: OD20013 | B14: 45354 | C14: Books | D14: Comic | E14: Rajasthan | F14: 1 | G14: 6814.15 | H14: 0.25 | I14: Cancelled | J14: Debit Card | K14: Mobile App | L14: 5110.61 | M14: =TEXT(B14,"mmm") -> Mar | N14: =IF(L14>20000,"high",IF(L14>10000,"medium","low")) -> low
A15: OD20014 | B15: 45397 | C15: Fashion | D15: Handbag | E15: Delhi | F15: 5 | G15: 2989.76 | H15: 0 | I15: Returned | J15: Wallet | K15: Mobile App | L15: 14948.8 | M15: =TEXT(B15,"mmm") -> Apr | N15: =IF(L15>20000,"high",IF(L15>10000,"medium","low")) -> medium
A16: OD20015 | B16: 45564 | C16: Fashion | D16: Jeans | E16: Up | F16: 5 | G16: 6265.58 | H16: 0.15 | I16: Pending | J16: Credit Card | K16: Mobile App | L16: 26628.72 | M16: =TEXT(B16,"mmm") -> Sep | N16: =IF(L16>20000,"high",IF(L16>10000,"medium","low")) -> high
A17: OD20016 | B17: 45474 | C17: Fashion | D17: Kurti | E17: Rajasthan | F17: 6 | G17: 377.49 | H17: 0 | I17: Delivered | J17: Debit Card | K17: Mobile App | L17: 2264.94 | M17: =TEXT(B17,"mmm") -> Jul | N17: =IF(L17>20000,"high",IF(L17>10000,"medium","low")) -> low
A18: OD20017 | B18: 45408 | C18: Electronics | D18: Power Bank | E18: Maharashtra | F18: 4 | G18: 1694.14 | H18: 0.1 | I18: Cancelled | J18: Debit Card | K18: Website | L18: 6098.9 | M18: =TEXT(B18,"mmm") -> Apr | N18: =IF(L18>20000,"high",IF(L18>10000,"medium","low")) -> low
A19: OD20018 | B19: 45536 | C19: Electronics | D19: Bluetooth Speaker | E19: Up | F19: 2 | G19: 3556.31 | H19: 0.15 | I19: Delivered | J19: UPI | K19: Mobile App | L19: 6045.73 | M19: =TEXT(B19,"mmm") -> Sep | N19: =IF(L19>20000,"high",IF(L19>10000,"medium","low")) -> low
A20: OD20019 | B20: 45369 | C20: Fashion | D20: Kurti | E20: Delhi | F20: 5 | G20: 7253.09 | H20: 0.05 | I20: Returned | J20: Wallet | K20: Mobile App | L20: 34452.18 | M20: =TEXT(B20,"mmm") -> Mar | N20: =IF(L20>20000,"high",IF(L20>10000,"medium","low")) -> high
A21: OD20020 | B21: 45561 | C21: Electronics | D21: Earbuds | E21: Maharashtra | F21: 6 | G21: 7478.95 | H21: 0.2 | I21: Delivered | J21: Credit Card | K21: Mobile App | L21: 35898.96 | M21: =TEXT(B21,"mmm") -> Sep | N21: =IF(L21>20000,"high",IF(L21>10000,"medium","low")) -> high
A22: OD20021 | B22: 45359 | C22: Home | D22: Curtain | E22: West Bengal | F22: 1 | G22: 7293.63 | H22: 0.15 | I22: Cancelled | J22: Wallet | K22: Mobile App | L22: 6199.59 | M22: =TEXT(B22,"mmm") -> Mar | N22: =IF(L22>20000,"high",IF(L22>10000,"medium","low")) -> low
A23: OD20022 | B23: 45517 | C23: Books | D23: Notebook | E23: Delhi | F23: 2 | G23: 4927.15 | H23: 0.05 | I23: Delivered | J23: Wallet | K23: Mobile App | L23: 9361.58 | M23: =TEXT(B23,"mmm") -> Aug | N23: =IF(L23>20000,"high",IF(L23>10000,"medium","low")) -> low
A24: OD20023 | B24: 45419 | C24: Electronics | D24: Phone Cover | E24: Delhi | F24: 2 | G24: 2323.8 | H24: 0 | I24: Returned | J24: Debit Card | K24: Mobile App | L24: 4647.6 | M24: =TEXT(B24,"mmm") -> May | N24: =IF(L24>20000,"high",IF(L24>10000,"medium","low")) -> low
A25: OD20024 | B25: 45551 | C25: Home | D25: Table Lamp | E25: Rajasthan | F25: 2 | G25: 5638.86 | H25: 0.1 | I25: Returned | J25: COD | K25: Mobile App | L25: 10149.95 | M25: =TEXT(B25,"mmm") -> Sep | N25: =IF(L25>20000,"high",IF(L25>10000,"medium","low")) -> medium
... A29: OD20028 | B29: 45335 | C29: Electronics | D29: Power Bank | E29: Maharashtra | F29: 3 | G29: 2284.58 | H29: 0.05 | I29: Delivered | J29: Debit Card | K29: Mobile App | L29: 6511.05 | M29: =TEXT(B29,"mmm") -> Feb | N29: =IF(L29>20000,"high",IF(L29>10000,"medium","low")) -> low
A30: OD20029 | B30: 45650 | C30: Fashion | D30: Handbag | E30: Rajasthan | F30: 3 | G30: 852.28 | H30: 0 | I30: Pending | J30: UPI | K30: Mobile App | L30: =(F30*G30)-(F30*G30)*H30 -> 2556.84 | M30: =TEXT(B30,"mmm") -> Dec | N30: =IF(L30>20000,"high",IF(L30>10000,"medium","low")) -> low
A31: OD20030 | B31: 45326 | C31: Electronics | D31: Phone Cover | E31: Up | F31: 3 | G31: 6922.78 | H31: 0.25 | I31: Delivered | J31: Credit Card | K31: Website | L31: 15576.26 | M31: =TEXT(B31,"mmm") -> Feb | N31: =IF(L31>20000,"high",IF(L31>10000,"medium","low")) -> medium
A32: OD20031 | B32: 45374 | C32: Books | D32: Notebook | E32: Maharashtra | F32: 3 | G32: 545.48 | H32: 0.1 | I32: Delivered | J32: Credit Card | K32: Mobile App | L32: 1472.8 | M32: =TEXT(B32,"mmm") -> Mar | N32: =IF(L32>20000,"high",IF(L32>10000,"medium","low")) -> low
A33: OD20032 | B33: 45310 | C33: Home | D33: Bedsheet | E33: Tamil Nadu | F33: 1 | G33: 294.71 | H33: 0.1 | I33: Returned | J33: COD | K33: Mobile App | L33: 265.24 | M33: =TEXT(B33,"mmm") -> Jan | N33: =IF(L33>20000,"high",IF(L33>10000,"medium","low")) -> low
A34: OD20033 | B34: 45644 | C34: Books | D34: Guide Book | E34: Tamil Nadu | F34: 2 | G34: 7862.16 | H34: 0.15 | I34: Delivered | J34: Debit Card | K34: Website | L34: 13365.67 | M34: =TEXT(B34,"mmm") -> Dec | N34: =IF(L34>20000,"high",IF(L34>10000,"medium","low")) -> medium
A35: OD20034 | B35: 45612 | C35: Fashion | D35: T-Shirt | E35: Maharashtra | F35: 6 | G35: 7056.86 | H35: 0.2 | I35: Delivered | J35: Debit Card | K35: Mobile App | L35: 33872.93 | M35: =TEXT(B35,"mmm") -> Nov | N35: =IF(L35>20000,"high",IF(L35>10000,"medium","low")) -> high
A36: OD20035 | B36: 45386 | C36: Home | D36: Bedsheet | E36: Rajasthan | F36: 2 | G36: 2261.94 | H36: 0 | I36: Delivered | J36: UPI | K36: Mobile App | L36: 4523.88 | M36: =TEXT(B36,"mmm") -> Apr | N36: =IF(L36>20000,"high",IF(L36>10000,"medium","low")) -> low
A37: OD20036 | B37: 45292 | C37: Fashion | D37: Jeans | E37: Karnataka | F37: 3 | G37: 3145.77 | H37: 0.25 | I37: Delivered | J37: Debit Card | K37: Website | L37: =(F37*G37)-(F37*G37)*H37 -> 7077.9825 | M37: =TEXT(B37,"mmm") -> Jan | N37: =IF(L37>20000,"high",IF(L37>10000,"medium","low")) -> low
A38: OD20037 | B38: 45493 | C38: Fashion | D38: Sneakers | E38: Delhi | F38: 1 | G38: 2502.22 | H38: 0.1 | I38: Delivered | J38: Wallet | K38: Mobile App | L38: 2252 | M38: =TEXT(B38,"mmm") -> Jul | N38: =IF(L38>20000,"high",IF(L38>10000,"medium","low")) -> low
A39: OD20038 | B39: 45437 | C39: Home | D39: Table Lamp | E39: Karnataka | F39: 6 | G39: 5006.85 | H39: 0.05 | I39: Delivered | J39: Wallet | K39: Mobile App | L39: 28539.05 | M39: =TEXT(B39,"mmm") -> May | N39: =IF(L39>20000,"high",IF(L39>10000,"medium","low")) -> high
A40: OD20039 | B40: 45643 | C40: Books | D40: Diary | E40: Delhi | F40: 5 | G40: 6414.04 | H40: 0.1 | I40: Delivered | J40: COD | K40: Website | L40: 28863.18 | M40: =TEXT(B40,"mmm") -> Dec | N40: =IF(L40>20000,"high",IF(L40>10000,"medium","low")) -> high
A41: OD20040 | B41: 45542 | C41: Electronics | D41: Phone Cover | E41: Up | F41: 3 | G41: 176.02 | H41: 0 | I41: Pending | J41: COD | K41: Mobile App | L41: 528.06 | M41: =TEXT(B41,"mmm") -> Sep | N41: =IF(L41>20000,"high",IF(L41>10000,"medium","low")) -> low
A42: OD20041 | B42: 45397 | C42: Electronics | D42: Smartwatch | E42: Up | F42: 2 | G42: 5957.65 | H42: 0.25 | I42: Cancelled | J42: UPI | K42: Mobile App | L42: 8936.47 | M42: =TEXT(B42,"mmm") -> Apr | N42: =IF(L42>20000,"high",IF(L42>10000,"medium","low")) -> low
A43: OD20042 | B43: 45461 | C43: Electronics | D43: Phone Cover | E43: Karnataka | F43: 3 | G43: 5264.54 | H43: 0.1 | I43: Returned | J43: UPI | K43: Mobile App | L43: 14214.26 | M43: =TEXT(B43,"mmm") -> Jun | N43: =IF(L43>20000,"high",IF(L43>10000,"medium","low")) -> medium
A44: OD20043 | B44: 45529 | C44: Beauty | D44: Perfume | E44: Tamil Nadu | F44: 4 | G44: 3810.76 | H44: 0 | I44: Returned | J44: COD | K44: Website | L44: =(F44*G44)-(F44*G44)*H44 -> 15243.04 | M44: =TEXT(B44,"mmm") -> Aug | N44: =IF(L44>20000,"high",IF(L44>10000,"medium","low")) -> medium
A45: OD20044 | B45: 45490 | C45: Books | D45: Guide Book | E45: Tamil Nadu | F45: 2 | G45: 7344.96 | H45: 0.1 | I45: Delivered | J45: Credit Card | K45: Mobile App | L45: 13220.93 | M45: =TEXT(B45,"mmm") -> Jul | N45: =IF(L45>20000,"high",IF(L45>10000,"medium","low")) -> medium
A46: OD20045 | B46: 45546 | C46: Electronics | D46: Smartwatch | E46: Up | F46: 4 | G46: 3243.53 | H46: 0.05 | I46: Delivered | J46: COD | K46: Mobile App | L46: 12325.41 | M46: =TEXT(B46,"mmm") -> Sep | N46: =IF(L46>20000,"high",IF(L46>10000,"medium","low")) -> medium
A47: OD20046 | B47: 45461 | C47: Beauty | D47: Perfume | E47: Maharashtra | F47: 1 | G47: 2697.7 | H47: 0.15 | I47: Cancelled | J47: Debit Card | K47: Mobile App | L47: 2293.04 | M47: =TEXT(B47,"mmm") -> Jun | N47: =IF(L47>20000,"high",IF(L47>10000,"medium","low")) -> low
A48: OD20047 | B48: 45491 | C48: Home | D48: Bedsheet | E48: West Bengal | F48: 5 | G48: 749.75 | H48: 0.2 | I48: Delivered | J48: Credit Card | K48: Mobile App | L48: 2999 | M48: =TEXT(B48,"mmm") -> Jul | N48: =IF(L48>20000,"high",IF(L48>10000,"medium","low")) -> low
A49: OD20048 | B49: 45389 | C49: Home | D49: Table Lamp | E49: Gujarat | F49: 3 | G49: 6313.37 | H49: 0.2 | I49: Delivered | J49: Wallet | K49: Mobile App | L49: 15152.09 | M49: =TEXT(B49,"mmm") -> Apr | N49: =IF(L49>20000,"high",IF(L49>10000,"medium","low")) -> medium
A50: OD20049 | B50: 45522 | C50: Electronics | D50: Earbuds | E50: West Bengal | F50: 5 | G50: 6058.44 | H50: 0.1 | I50: Cancelled | J50: Debit Card | K50: Mobile App | L50: 27262.98 | M50: =TEXT(B50,"mmm") -> Aug | N50: =IF(L50>20000,"high",IF(L50>10000,"medium","low")) -> high
A51: OD20050 | B51: 45499 | C51: Home | D51: Cushion | E51: Tamil Nadu | F51: 6 | G51: 2023.52 | H51: 0.25 | I51: Returned | J51: Wallet | K51: Mobile App | L51: 9105.84 | M51: =TEXT(B51,"mmm") -> Jul | N51: =IF(L51>20000,"high",IF(L51>10000,"medium","low")) -> low
A52: OD20051 | B52: 45462 | C52: Books | D52: Notebook | E52: Rajasthan | F52: 4 | G52: 3505.27 | H52: 0.1 | I52: Delivered | J52: Debit Card | K52: Mobile App | L52: 12618.97 | M52: =TEXT(B52,"mmm") -> Jun | N52: =IF(L52>20000,"high",IF(L52>10000,"medium","low")) -> medium
A53: OD20052 | B53: 45503 | C53: Electronics | D53: Bluetooth Speaker | E53: West Bengal | F53: 6 | G53: 4264.72 | H53: 0.2 | I53: Delivered | J53: Credit Card | K53: Mobile App | L53: 20470.66 | M53: =TEXT(B53,"mmm") -> Jul | N53: =IF(L53>20000,"high",IF(L53>10000,"medium","low")) -> high
A54: OD20053 | B54: 45488 | C54: Electronics | D54: Smartwatch | E54: Up | F54: 4 | G54: 5219.46 | H54: 0.2 | I54: Delivered | J54: COD | K54: Mobile App | L54: 16702.27 | M54: =TEXT(B54,"mmm") -> Jul | N54: =IF(L54>20000,"high",IF(L54>10000,"medium","low")) -> medium
A55: OD20054 | B55: 45562 | C55: Electronics | D55: Earbuds | E55: West Bengal | F55: 4 | G55: 7782.09 | H55: 0.1 | I55: Delivered | J55: COD | K55: Website | L55: 28015.52 | M55: =TEXT(B55,"mmm") -> Sep | N55: =IF(L55>20000,"high",IF(L55>10000,"medium","low")) -> high
A56: OD20055 | B56: 45356 | C56: Books | D56: Novel | E56: Delhi | F56: 2 | G56: 4619.65 | H56: 0 | I56: Pending | J56: COD | K56: Website | L56: 9239.3 | M56: =TEXT(B56,"mmm") -> Mar | N56: =IF(L56>20000,"high",IF(L56>10000,"medium","low")) -> low
... A109: OD20108 | B109: 45367 | C109: Fashion | D109: Sneakers | E109: Karnataka | F109: 3 | G109: 5906.35 | H109: 0.2 | I109: Delivered | J109: COD | K109: Mobile App | L109: 14175.24 | M109: =TEXT(B109,"mmm") -> Mar | N109: =IF(L109>20000,"high",IF(L109>10000,"medium","low")) -> medium
A110: OD20109 | B110: 45515 | C110: Electronics | D110: Earbuds | E110: West Bengal | F110: 6 | G110: 1896.25 | H110: 0.1 | I110: Cancelled | J110: Credit Card | K110: Mobile App | L110: =(F110*G110)-(F110*G110)*H110 -> 10239.75 | M110: =TEXT(B110,"mmm") -> Aug | N110: =IF(L110>20000,"high",IF(L110>10000,"medium","low")) -> medium
A111: OD20110 | B111: 45409 | C111: Books | D111: Diary | E111: West Bengal | F111: 6 | G111: 5819.42 | H111: 0.1 | I111: Pending | J111: UPI | K111: Mobile App | L111: 31424.87 | M111: =TEXT(B111,"mmm") -> Apr | N111: =IF(L111>20000,"high",IF(L111>10000,"medium","low")) -> high
A112: OD20111 | B112: 45420 | C112: Fashion | D112: Sneakers | E112: Karnataka | F112: 4 | G112: 3939.54 | H112: 0 | I112: Returned | J112: Debit Card | K112: Website | L112: 15758.16 | M112: =TEXT(B112,"mmm") -> May | N112: =IF(L112>20000,"high",IF(L112>10000,"medium","low")) -> medium
A113: OD20112 | B113: 45311 | C113: Beauty | D113: Hair Oil | E113: Maharashtra | F113: 3 | G113: 4415.38 | H113: 0.05 | I113: Pending | J113: Wallet | K113: Mobile App | L113: 12583.83 | M113: =TEXT(B113,"mmm") -> Jan | N113: =IF(L113>20000,"high",IF(L113>10000,"medium","low")) -> medium
A114: OD20113 | B114: 45554 | C114: Books | D114: Notebook | E114: Rajasthan | F114: 1 | G114: 5168.2 | H114: 0.15 | I114: Returned | J114: Credit Card | K114: Mobile App | L114: 4392.97 | M114: =TEXT(B114,"mmm") -> Sep | N114: =IF(L114>20000,"high",IF(L114>10000,"medium","low")) -> low
A115: OD20114 | B115: 45618 | C115: Books | D115: Novel | E115: Gujarat | F115: 1 | G115: 2131.79 | H115: 0.2 | I115: Cancelled | J115: Debit Card | K115: Mobile App | L115: 1705.43 | M115: =TEXT(B115,"mmm") -> Nov | N115: =IF(L115>20000,"high",IF(L115>10000,"medium","low")) -> low
A116: OD20115 | B116: 45497 | C116: Electronics | D116: Power Bank | E116: Tamil Nadu | F116: 5 | G116: 7776.28 | H116: 0.2 | I116: Cancelled | J116: Credit Card | K116: Mobile App | L116: 31105.12 | M116: =TEXT(B116,"mmm") -> Jul | N116: =IF(L116>20000,"high",IF(L116>10000,"medium","low")) -> high
A117: OD20116 | B117: 45472 | C117: Books | D117: Notebook | E117: Karnataka | F117: 6 | G117: 5164.55 | H117: 0.2 | I117: Cancelled | J117: COD | K117: Mobile App | L117: 24789.84 | M117: =TEXT(B117,"mmm") -> Jun | N117: =IF(L117>20000,"high",IF(L117>10000,"medium","low")) -> high
A118: OD20117 | B118: 45643 | C118: Fashion | D118: Jeans | E118: West Bengal | F118: 3 | G118: 7865.69 | H118: 0.05 | I118: Cancelled | J118: Debit Card | K118: Mobile App | L118: 22417.22 | M118: =TEXT(B118,"mmm") -> Dec | N118: =IF(L118>20000,"high",IF(L118>10000,"medium","low")) -> high
A119: OD20118 | B119: 45611 | C119: Beauty | D119: Hair Oil | E119: West Bengal | F119: 6 | G119: 820.56 | H119: 0.15 | I119: Delivered | J119: Debit Card | K119: Mobile App | L119: 4184.86 | M119: =TEXT(B119,"mmm") -> Nov | N119: =IF(L119>20000,"high",IF(L119>10000,"medium","low")) -> low
A120: OD20119 | B120: 45628 | C120: Books | D120: Comic | E120: Delhi | F120: 1 | G120: 1796.53 | H120: 0 | I120: Pending | J120: Credit Card | K120: Mobile App | L120: 1796.53 | M120: =TEXT(B120,"mmm") -> Dec | N120: =IF(L120>20000,"high",IF(L120>10000,"medium","low")) -> low
A121: OD20120 | B121: 45498 | C121: Home | D121: Wall Clock | E121: Up | F121: 5 | G121: 1468.12 | H121: 0 | I121: Pending | J121: COD | K121: Mobile App | L121: 7340.6 | M121: =TEXT(B121,"mmm") -> Jul | N121: =IF(L121>20000,"high",IF(L121>10000,"medium","low")) -> low
A122: OD20121 | B122: 45635 | C122: Books | D122: Novel | E122: Rajasthan | F122: 1 | G122: 4507.25 | H122: 0.1 | I122: Cancelled | J122: COD | K122: Mobile App | L122: 4056.53 | M122: =TEXT(B122,"mmm") -> Dec | N122: =IF(L122>20000,"high",IF(L122>10000,"medium","low")) -> low
... A171: OD20170 | B171: 45503 | C171: Beauty | D171: Perfume | E171: Karnataka | F171: 1 | G171: 183.94 | H171: 0 | I171: Cancelled | J171: Debit Card | K171: Website | L171: 183.94 | M171: =TEXT(B171,"mmm") -> Jul | N171: =IF(L171>20000,"high",IF(L171>10000,"medium","low")) -> low
A172: OD20171 | B172: 45439 | C172: Beauty | D172: Hair Oil | E172: Rajasthan | F172: 6 | G172: 2918.06 | H172: 0.15 | I172: Cancelled | J172: COD | K172: Mobile App | L172: =(F172*G172)-(F172*G172)*H172 -> 14882.106 | M172: =TEXT(B172,"mmm") -> May | N172: =IF(L172>20000,"high",IF(L172>10000,"medium","low")) -> medium
A173: OD20172 | B173: 45566 | C173: Beauty | D173: Perfume | E173: Karnataka | F173: 3 | G173: 6453.18 | H173: 0.2 | I173: Returned | J173: Wallet | K173: Mobile App | L173: 15487.63 | M173: =TEXT(B173,"mmm") -> Oct | N173: =IF(L173>20000,"high",IF(L173>10000,"medium","low")) -> medium
A174: OD20173 | B174: 45297 | C174: Home | D174: Wall Clock | E174: West Bengal | F174: 1 | G174: 522.42 | H174: 0.25 | I174: Delivered | J174: Wallet | K174: Mobile App | L174: 391.81 | M174: =TEXT(B174,"mmm") -> Jan | N174: =IF(L174>20000,"high",IF(L174>10000,"medium","low")) -> low
A175: OD20174 | B175: 45312 | C175: Beauty | D175: Hair Oil | E175: Gujarat | F175: 5 | G175: 5458.38 | H175: 0.25 | I175: Delivered | J175: COD | K175: Mobile App | L175: 20468.93 | M175: =TEXT(B175,"mmm") -> Jan | N175: =IF(L175>20000,"high",IF(L175>10000,"medium","low")) -> high
A176: OD20175 | B176: 45497 | C176: Fashion | D176: Sneakers | E176: Rajasthan | F176: 4 | G176: 6173.53 | H176: 0.15 | I176: Pending | J176: UPI | K176: Mobile App | L176: 20990 | M176: =TEXT(B176,"mmm") -> Jul | N176: =IF(L176>20000,"high",IF(L176>10000,"medium","low")) -> high
A177: OD20176 | B177: 45627 | C177: Books | D177: Notebook | E177: Maharashtra | F177: 3 | G177: 5565.61 | H177: 0.2 | I177: Pending | J177: Credit Card | K177: Mobile App | L177: 13357.46 | M177: =TEXT(B177,"mmm") -> Dec | N177: =IF(L177>20000,"high",IF(L177>10000,"medium","low")) -> medium
A178: OD20177 | B178: 45472 | C178: Fashion | D178: T-Shirt | E178: Maharashtra | F178: 5 | G178: 7950.93 | H178: 0 | I178: Pending | J178: UPI | K178: Mobile App | L178: 39754.65 | M178: =TEXT(B178,"mmm") -> Jun | N178: =IF(L178>20000,"high",IF(L178>10000,"medium","low")) -> high
A179: OD20178 | B179: 45634 | C179: Beauty | D179: Face Wash | E179: Delhi | F179: 1 | G179: 1693.71 | H179: 0.25 | I179: Returned | J179: Credit Card | K179: Mobile App | L179: 1270.28 | M179: =TEXT(B179,"mmm") -> Dec | N179: =IF(L179>20000,"high",IF(L179>10000,"medium","low")) -> low
A180: OD20179 | B180: 45366 | C180: Beauty | D180: Sunscreen | E180: Maharashtra | F180: 2 | G180: 4219.63 | H180: 0 | I180: Delivered | J180: Wallet | K180: Mobile App | L180: 8439.26 | M180: =TEXT(B180,"mmm") -> Mar | N180: =IF(L180>20000,"high",IF(L180>10000,"medium","low")) -> low
A181: OD20180 | B181: 45365 | C181: Electronics | D181: Earbuds | E181: Gujarat | F181: 6 | G181: 2020.36 | H181: 0.1 | I181: Delivered | J181: UPI | K181: Mobile App | L181: 10909.94 | M181: =TEXT(B181,"mmm") -> Mar | N181: =IF(L181>20000,"high",IF(L181>10000,"medium","low")) -> medium
A182: OD20181 | B182: 45302 | C182: Fashion | D182: Sneakers | E182: West Bengal | F182: 1 | G182: 1877.38 | H182: 0.2 | I182: Returned | J182: Credit Card | K182: Website | L182: 1501.9 | M182: =TEXT(B182,"mmm") -> Jan | N182: =IF(L182>20000,"high",IF(L182>10000,"medium","low")) -> low
A183: OD20182 | B183: 45453 | C183: Fashion | D183: Handbag | E183: Karnataka | F183: 1 | G183: 7206.11 | H183: 0.25 | I183: Delivered | J183: UPI | K183: Mobile App | L183: 5404.58 | M183: =TEXT(B183,"mmm") -> Jun | N183: =IF(L183>20000,"high",IF(L183>10000,"medium","low")) -> low
A184: OD20183 | B184: 45503 | C184: Beauty | D184: Sunscreen | E184: Up | F184: 3 | G184: 3278.99 | H184: 0.25 | I184: Delivered | J184: Credit Card | K184: Website | L184: 7377.73 | M184: =TEXT(B184,"mmm") -> Jul | N184: =IF(L184>20000,"high",IF(L184>10000,"medium","low")) -> low
... A206: OD20205 | B206: 45362 | C206: Fashion | D206: Kurti | E206: Karnataka | F206: 4 | G206: 5148.53 | H206: 0.2 | I206: Delivered | J206: Debit Card | K206: Website | L206: 16475.3 | M206: =TEXT(B206,"mmm") -> Mar | N206: =IF(L206>20000,"high",IF(L206>10000,"medium","low")) -> medium
A207: OD20206 | B207: 45365 | C207: Electronics | D207: Phone Cover | E207: West Bengal | F207: 3 | G207: 715.15 | H207: 0 | I207: Returned | J207: Credit Card | K207: Mobile App | L207: =(F207*G207)-(F207*G207)*H207 -> 2145.45 | M207: =TEXT(B207,"mmm") -> Mar | N207: =IF(L207>20000,"high",IF(L207>10000,"medium","low")) -> low
A208: OD20207 | B208: 45518 | C208: Beauty | D208: Perfume | E208: Delhi | F208: 5 | G208: 5450.8 | H208: 0.1 | I208: Cancelled | J208: Credit Card | K208: Mobile App | L208: 24528.6 | M208: =TEXT(B208,"mmm") -> Aug | N208: =IF(L208>20000,"high",IF(L208>10000,"medium","low")) -> high
A209: OD20208 | B209: 45322 | C209: Books | D209: Diary | E209: Maharashtra | F209: 6 | G209: 5460.1 | H209: 0.1 | I209: Returned | J209: Debit Card | K209: Mobile App | L209: 29484.54 | M209: =TEXT(B209,"mmm") -> Jan | N209: =IF(L209>20000,"high",IF(L209>10000,"medium","low")) -> high
A210: OD20209 | B210: 45405 | C210: Books | D210: Novel | E210: Up | F210: 6 | G210: 5956.77 | H210: 0 | I210: Delivered | J210: Wallet | K210: Mobile App | L210: 35740.62 | M210: =TEXT(B210,"mmm") -> Apr | N210: =IF(L210>20000,"high",IF(L210>10000,"medium","low")) -> high
A211: OD20210 | B211: 45425 | C211: Books | D211: Guide Book | E211: West Bengal | F211: 1 | G211: 1933.87 | H211: 0.1 | I211: Returned | J211: Credit Card | K211: Mobile App | L211: 1740.48 | M211: =TEXT(B211,"mmm") -> May | N211: =IF(L211>20000,"high",IF(L211>10000,"medium","low")) -> low
A212: OD20211 | B212: 45407 | C212: Beauty | D212: Lipstick | E212: Rajasthan | F212: 5 | G212: 4645.75 | H212: 0 | I212: Pending | J212: UPI | K212: Mobile App | L212: 23228.75 | M212: =TEXT(B212,"mmm") -> Apr | N212: =IF(L212>20000,"high",IF(L212>10000,"medium","low")) -> high
A213: OD20212 | B213: 45612 | C213: Fashion | D213: Handbag | E213: Maharashtra | F213: 6 | G213: 4193.98 | H213: 0.25 | I213: Pending | J213: UPI | K213: Mobile App | L213: 18872.91 | M213: =TEXT(B213,"mmm") -> Nov | N213: =IF(L213>20000,"high",IF(L213>10000,"medium","low")) -> medium
A214: OD20213 | B214: 45499 | C214: Home | D214: Curtain | E214: Delhi | F214: 2 | G214: 520.69 | H214: 0 | I214: Delivered | J214: Credit Card | K214: Mobile App | L214: 1041.38 | M214: =TEXT(B214,"mmm") -> Jul | N214: =IF(L214>20000,"high",IF(L214>10000,"medium","low")) -> low
A215: OD20214 | B215: 45580 | C215: Electronics | D215: Phone Cover | E215: Up | F215: 1 | G215: 7352.41 | H215: 0.15 | I215: Delivered | J215: UPI | K215: Mobile App | L215: 6249.55 | M215: =TEXT(B215,"mmm") -> Oct | N215: =IF(L215>20000,"high",IF(L215>10000,"medium","low")) -> low
A216: OD20215 | B216: 45554 | C216: Electronics | D216: Power Bank | E216: Gujarat | F216: 6 | G216: 4268.96 | H216: 0.15 | I216: Pending | J216: Debit Card | K216: Website | L216: 21771.7 | M216: =TEXT(B216,"mmm") -> Sep | N216: =IF(L216>20000,"high",IF(L216>10000,"medium","low")) -> high
A217: OD20216 | B217: 45473 | C217: Electronics | D217: Power Bank | E217: Tamil Nadu | F217: 2 | G217: 5597.33 | H217: 0 | I217: Returned | J217: Debit Card | K217: Mobile App | L217: 11194.66 | M217: =TEXT(B217,"mmm") -> Jun | N217: =IF(L217>20000,"high",IF(L217>10000,"medium","low")) -> medium
A218: OD20217 | B218: 45643 | C218: Fashion | D218: Handbag | E218: Tamil Nadu | F218: 6 | G218: 3139.44 | H218: 0.05 | I218: Returned | J218: COD | K218: Website | L218: 17894.81 | M218: =TEXT(B218,"mmm") -> Dec | N218: =IF(L218>20000,"high",IF(L218>10000,"medium","low")) -> medium
A219: OD20218 | B219: 45541 | C219: Electronics | D219: Smartwatch | E219: Karnataka | F219: 5 | G219: 3949.16 | H219: 0 | I219: Delivered | J219: COD | K219: Mobile App | L219: 19745.8 | M219: =TEXT(B219,"mmm") -> Sep | N219: =IF(L219>20000,"high",IF(L219>10000,"medium","low")) -> medium
... A229: OD20228 | B229: 45619 | C229: Fashion | D229: Jeans | E229: Delhi | F229: 3 | G229: 7394.67 | H229: 0.1 | I229: Delivered | J229: Debit Card | K229: Mobile App | L229: 19965.61 | M229: =TEXT(B229,"mmm") -> Nov | N229: =IF(L229>20000,"high",IF(L229>10000,"medium","low")) -> medium
A230: OD20229 | B230: 45336 | C230: Electronics | D230: Bluetooth Speaker | E230: Delhi | F230: 6 | G230: 4960.42 | H230: 0.25 | I230: Returned | J230: Debit Card | K230: Mobile App | L230: =(F230*G230)-(F230*G230)*H230 -> 22321.89 | M230: =TEXT(B230,"mmm") -> Feb | N230: =IF(L230>20000,"high",IF(L230>10000,"medium","low")) -> high
A231: OD20230 | B231: 45372 | C231: Electronics | D231: Bluetooth Speaker | E231: Gujarat | F231: 1 | G231: 296.02 | H231: 0.1 | I231: Delivered | J231: Debit Card | K231: Mobile App | L231: 266.42 | M231: =TEXT(B231,"mmm") -> Mar | N231: =IF(L231>20000,"high",IF(L231>10000,"medium","low")) -> low
A232: OD20231 | B232: 45409 | C232: Books | D232: Diary | E232: Gujarat | F232: 6 | G232: 5006.61 | H232: 0.25 | I232: Delivered | J232: COD | K232: Mobile App | L232: 22529.74 | M232: =TEXT(B232,"mmm") -> Apr | N232: =IF(L232>20000,"high",IF(L232>10000,"medium","low")) -> high
A233: OD20232 | B233: 45359 | C233: Home | D233: Curtain | E233: Tamil Nadu | F233: 3 | G233: 220.97 | H233: 0.25 | I233: Delivered | J233: Credit Card | K233: Mobile App | L233: 497.18 | M233: =TEXT(B233,"mmm") -> Mar | N233: =IF(L233>20000,"high",IF(L233>10000,"medium","low")) -> low
...

Sheet analysis
A1: Extracted Text from the Image
A3: Business Question | B3: Formula
A4: Total Orders kitne? | B4: =COUNTA(OrderID)
A5: Total Revenue? | B5: =SUM(OrderAmount)
A6: Average Order Value? | B6: =AVERAGE(OrderAmount)
A7: Delivered orders? | B7: =COUNTIF(Status,"Delivered")
A8: Cancelled orders? | B8: =COUNTIF(Status,"Cancelled")
A9: UPI se kitna revenue? | B9: =SUMIF(Pay,"UPI",Amount)
A10: App vs Website orders? | B10: =COUNTIF(Channel,"Mobile App")
A11: Electronics ka revenue? | B11: =SUMIF(Cat,"Electronics",Amount)
A13: Business Questions in Simple Form
A15: 1. Total Orders? | B15: =COUNTA(Table1[OrderID]) -> 1100
A17: 2. Total Revenue? | B17: =SUM(Table1[OrderAmount]) -> 13437722
A19: 3. Average Order Value? | B19: =AVERAGE('Ecommerce_Raw_Data (2)'!L1071:L1101) -> 10886.493
A21: 4. Delivered Orders? | B21: =COUNTIF(Table1[OrderStatus],'Ecommerce_Raw_Data (2)'!I1072) -> 554
A23: 5. Cancelled Orders? | B23: =COUNTIF(Table1[OrderStatus],'Ecommerce_Raw_Data (2)'!I1077) -> 177
A25: 6. Revenue from UPI Payments? | B25: =SUMIF(Table1[PaymentMode],"upi",Table1[OrderAmount]) -> 2734927.4
A27: 7. Mobile App vs Website Orders? | B27: =COUNTIF(Table1[Channel],'Ecommerce_Raw_Data (2)'!K1071) -> 841
A29: 8. Revenue from Electronics Category? | B29: =SUMIF(Table1[Category],'Ecommerce_Raw_Data (2)'!C1097,Table1[OrderAmount]) -> 2547506.6

Sheet pivot
A1: Category Revenue | E1: State Revenue | H1: Month Trend | K1: Status Count
A2: Row Labels | B2: Sum of OrderAmount | E2: Row Labels | F2: Sum of OrderAmount | H2: Row Labels | I2: Sum of OrderAmount | K2: Row Labels | L2: Count of OrderID | N2: Count of OrderID
A3: Beauty | B3: 2580125.7 | E3: Delhi | F3: 1647601.5 | H3: Jan | I3: 890424.49 | K3: Cancelled | L3: 177 | N3: 1100
A4: Books | B4: 2899898.1 | E4: Gujarat | F4: 1400504.8 | H4: Feb | I4: 1188321.7 | K4: Delivered | L4: 554
A5: Electronics | B5: 2547506.6 | E5: Karnataka | F5: 1484774.8 | H5: Mar | I5: 1310963.7 | K5: Pending | L5: 189 | N5: Average of OrderAmount
A6: Fashion | B6: 3200616.5 | E6: Maharashtra | F6: 2049161.2 | H6: Apr | I6: 1017549.3 | K6: Returned | L6: 180 | N6: 12216.111
A7: Home | B7: 2209574.6 | E7: Rajasthan | F7: 1654906.4 | H7: May | I7: 964522.14 | K7: Grand Total | L7: 1100
A8: Grand Total | B8: 13437722 | E8: Tamil Nadu | F8: 1706124.8 | H8: Jun | I8: 1256588.8 | N8: Sum of OrderAmount
E9: Up | F9: 1697372.7 | H9: Jul | I9: 1470854.8 | N9: 13437722
E10: West Bengal | F10: 1797275.4 | H10: Aug | I10: 1002404.1
E11: Grand Total | F11: 13437722 | H11: Sep | I11: 1141100.5 | N11: Row Labels | O11: Count of OrderAmount
H12: Oct | I12: 1274850.4 | N12: Delivered | O12: 554
H13: Nov | I13: 932916.36 | N13: Grand Total | O13: 554
H14: Dec | I14: 987225.39
H15: Grand Total | I15: 13437722
E18: Channel Split | H18: Payment Mode
E19: Row Labels | F19: Sum of OrderAmount | H19: Row Labels | I19: Sum of OrderAmount
E20: Mobile App | F20: 10090942 | H20: COD | I20: 2688398.2
E21: Website | F21: 3346779.4 | H21: Credit Card | I21: 2356422.1
E22: Grand Total | F22: 13437722 | H22: Debit Card | I22: 2669094
H23: UPI | I23: 2734927.4
H24: Wallet | I24: 2988880

Sheet dashboard
